functions.py
libros-1.0.0.dist-info/METADATA
libros-1.0.0.dist-info/WHEEL
libros-1.0.0.dist-info/top_level.txt
libros-1.0.0.dist-info/RECORD
