Metadata-Version: 2.1
Name: libros
Version: 1.0.0
Summary: busqueda de libros por medio de isbn
Author: itzel franco 
Author-email: itzel_fd1@tesch.edu.mx
Requires-Dist: pandas
Requires-Dist: tkinter
